modicon/__init__.py
modicon/http/__init__.py
modicon/http/fastapi/__init__.py
modicon/http/fastapi/container.py
modicon_http_fastapi-0.1.2.dist-info/licenses/LICENSE
modicon_http_fastapi-0.1.2.dist-info/METADATA
modicon_http_fastapi-0.1.2.dist-info/WHEEL
modicon_http_fastapi-0.1.2.dist-info/top_level.txt
modicon_http_fastapi-0.1.2.dist-info/RECORD
