Metadata-Version: 2.4
Name: modicon-http-fastapi
Version: 0.1.2
Summary: Modicon HTTP FastAPI Integration
Author-email: Kostia Tarnashynskyi <kostia.tarnashynskyi@gmail.com>
Maintainer-email: Kostia Tarnashynskyi <kostia.tarnashynskyi@gmail.com>
License-Expression: MIT
Project-URL: Homepage, https://github.com/kostia-tarnashynskyi/modicon-rest-fastapi
Project-URL: Documentation, https://github.com/kostia-tarnashynskyi/modicon-rest-fastapi#readme
Project-URL: Repository, https://github.com/kostia-tarnashynskyi/modicon-rest-fastapi
Keywords: fastapi,rest,http,api,web,di,dependency injection,framework,python
Classifier: Development Status :: 3 - Alpha
Classifier: Intended Audience :: Developers
Classifier: Operating System :: OS Independent
Classifier: Programming Language :: Python :: 3
Classifier: Programming Language :: Python :: 3.9
Classifier: Programming Language :: Python :: 3.10
Classifier: Programming Language :: Python :: 3.11
Classifier: Programming Language :: Python :: 3.12
Classifier: Programming Language :: Python :: 3.13
Classifier: Topic :: Software Development :: Libraries :: Python Modules
Requires-Python: <4.0,>=3.11
License-File: LICENSE
Requires-Dist: dependency-injector>=4.48.1
Requires-Dist: fastapi>=0.116.1
Dynamic: license-file
